<contentList>
	<content contentuid="h03c86dcdgfd76g4999gb300g6f53be6dcbb7">Zebadiah</content>
	<content contentuid="h10a57d7cg0ac2g469dgb674g161294824352">Perpetual Appetence</content>
	<content contentuid="h2a691813g0bf5g49b5g91ddg580d7978c18a">Upon a mound of corpses, in a strange lab filled with flesh and strange machines, your mind snapped into consciousness. An unending abyss where your soul once resided, you persist with a singular desire - Tearing apart the one who did this to you.</content>
	<content contentuid="h2f045ef5g2b2ag4f77gba27gb6832cb04fd0">&lt;font color=&apos;#44FF00&apos;&gt;[1] devoured [2].&lt;/font&gt;</content>
	<content contentuid="h51919b5dgc0bfg4db8g97ccg049d8df5fed9">All-Consuming Hunger</content>
	<content contentuid="h5c98296agd425g4303gb985gd772c9207290">The last great war wrought devastation on all the races. You remember first-hand the massacre of your people. While the world continued to spin, your resolve only aged like a great tree - battered by time, yet steadfast and unyielding.</content>
	<content contentuid="h61152cc2g32fdg4763gbbfcg01b202a18a76">Deku&apos;Deku</content>
	<content contentuid="h66fa7059g0221g42c1ga3f5gd8ad191b33da">Null</content>
	<content contentuid="h6774095eg201fg44b0g8f82gc8a1c394b3dd">&lt;font color=&apos;#FF4400&apos;&gt;[1] resists being consumed!&lt;/font&gt;</content>
	<content contentuid="h679e2e10g7daeg4ae7g8ce8ge7ab4ebe9980">Devour Weak Targets[1]</content>
	<content contentuid="h692f86bdg95b1g4332ga07eg060d823eb98b">Spreads your demonic wings. You ignore ground surfaces as long as you&apos;re walking.</content>
	<content contentuid="h70efcf2fg6463g4050gb4b7gd611ac35e35f">Edacious Reprieve</content>
	<content contentuid="h73a38336gff1eg452agbea9g690dbb69309f">After breaching the material plane, you find a world ripe with source. Let the feast begin.</content>
	<content contentuid="h8d7db582g41fag4ef2gb9dcgd205ef66ad1a">You awoke to a body made of plush. Roaming the land in search of kin, armed only with your own sense of justice, you sought answers to the nature of your being, yet the Magistry deemed you an abomination. Time to deliver some &quot;Bear Justice&quot;.</content>
	<content contentuid="h91df470dgfc23g4d65g8b5cgcc926515c911">Berobreus</content>
	<content contentuid="h9449fc86g8ddcg44cagb59fg37d4deae4d96">Spread Your Wings</content>
	<content contentuid="ha8a2dbbegb20cg498egb08ag8646c0088239">&lt;font color=&apos;#44FF00&apos;&gt;Consumed [1]!&lt;/font&gt;</content>
	<content contentuid="hae0b1abag1f6cg40beg89dag1f4d5082796d">While other &quot;conscious undead&quot; exist purely in skeleton form, your flesh persists, rotten skin and all. Others of your kind mindlessly shamble, yet you ponder and roam purposefully. Sure, brains taste good, but that&apos;s just how it is.</content>
	<content contentuid="hb89e911cg9c18g400dg80acg315705223458">Devour the weak to proliferate your demonic vigour.</content>
	<content contentuid="hc33df90dg724bg4f2dg91f3gec26aa2427a4">Hunger is sated, reap the rewards.</content>
	<content contentuid="hd271c1ffg2a8ag4df2gbc3fgc0538424f267">The hunger persists. Lose [1] Source Point on ending turn.</content>
	<content contentuid="hec620481g3b28g493cg846bg800583e0b8f0">Oberon</content>
	<content contentuid="hf6c1eb6cg719eg4e7bg9ae2gba38df986433">&lt;font color=&apos;#FF4400&apos;&gt;[1] failed to devour [2]: [3]&lt;/font&gt;</content>
</contentList>
